pyStressTest/__init__.py
pyStressTest/main.py
pyStressTest/monitor.py
pyStressTest/stress_test.py
pyStressTest/abstarct/__init__.py
pyStressTest/abstarct/monitor.py
pyStressTest/abstarct/stress_test.py
pyStressTest-1.2.2.dist-info/LICENSE.txt
pyStressTest-1.2.2.dist-info/METADATA
pyStressTest-1.2.2.dist-info/WHEEL
pyStressTest-1.2.2.dist-info/top_level.txt
pyStressTest-1.2.2.dist-info/zip-safe
pyStressTest-1.2.2.dist-info/RECORD
