Metadata-Version: 2.1
Name: pyStressTest
Version: 1.2.2
Summary: Module for resource stress testing and automatic statistics generation
Home-page: https://github.com/Ryize/pyStressTest
Author: Chekashov Matvey/Ryize
Author-email: chekashovmatvey@gmail.com
License: MIT
Platform: UNKNOWN
License-File: LICENSE.txt
Requires-Dist: requests
Requires-Dist: matplotlib
